CHANGES.txt
MANIFEST.in
README.md
TODO.org
base.cfg
bootstrap.py
buildout-plone3.cfg
buildout-plone4.cfg
buildout.cfg
requirements-4.3.txt
requirements-5.2.txt
setup.py
test-4.3.cfg
test-5.2.cfg
src/slc/__init__.py
src/slc.outdated.egg-info/PKG-INFO
src/slc.outdated.egg-info/SOURCES.txt
src/slc.outdated.egg-info/dependency_links.txt
src/slc.outdated.egg-info/entry_points.txt
src/slc.outdated.egg-info/namespace_packages.txt
src/slc.outdated.egg-info/not-zip-safe
src/slc.outdated.egg-info/requires.txt
src/slc.outdated.egg-info/top_level.txt
src/slc/outdated/__init__.py
src/slc/outdated/adapter.py
src/slc/outdated/browser.py
src/slc/outdated/configure.zcml
src/slc/outdated/event.py
src/slc/outdated/interfaces.py
src/slc/outdated/outdated.png
src/slc/outdated/outdated_mini.png
src/slc/outdated/utils.py
src/slc/outdated/viewlet.pt
src/slc/outdated/viewlet.py
src/slc/outdated/profile/actions.xml
src/slc/outdated/profile/browserlayer.xml
src/slc/outdated/profile/catalog.xml
src/slc/outdated/profile/metadata.xml
src/slc/outdated/tests/__init__.py
src/slc/outdated/tests/base.py
src/slc/outdated/tests/test_adapter.py
src/slc/outdated/tests/test_setup.py
src/slc/outdated/tests/test_toggle.py
src/slc/outdated/tests/test_utils.py