Metadata-Version: 2.1
Name: slc.outdated
Version: 1.3.1
Summary: Mark and treat plone content as outdated
Home-page: https://github.com/collective/slc.outdated
Author: Florian Friesdorf
Author-email: friesdorf@syslab.com
License: General Public Licence
Platform: UNKNOWN
Classifier: Development Status :: 4 - Beta
Classifier: Environment :: Web Environment
Classifier: Framework :: Plone
Classifier: Framework :: Plone :: Addon
Classifier: Framework :: Plone :: 5.2
Classifier: License :: OSI Approved :: GNU General Public License (GPL)
Classifier: Operating System :: OS Independent
Classifier: Programming Language :: Python
Classifier: Programming Language :: Python :: 2.7
Classifier: Programming Language :: Python :: 3.6
Classifier: Programming Language :: Python :: 3.7
Provides-Extra: test
